gRNA_create/__init__.py
gRNA_create/gRNA.py
gRNA_create/gRNA_genetic_algorithm.py
gRNA_create/gRNA_scorer.py
gRNA_create/gRNA_visualize.py
gRNA_create/pam.py
gRNA_create/py.typed
gRNA_create/utils.py
gRNA_create-0.0.2.dist-info/LICENSE
gRNA_create-0.0.2.dist-info/METADATA
gRNA_create-0.0.2.dist-info/WHEEL
gRNA_create-0.0.2.dist-info/top_level.txt
gRNA_create-0.0.2.dist-info/RECORD
