Metadata-Version: 2.1
Name: gRNA-create
Version: 0.0.2
Summary: A tool to create gRNAs
Home-page: https://github.com/ArmaanAhmed22/gRNA_create
Author: Armaan Ahmed
Author-email: aahmedresearch@gmail.com
License: MIT
Project-URL: Bug Tracker, https://github.com/ArmaanAhmed22/gRNA_create/issues
Platform: unix
Platform: linux
Platform: osx
Platform: cygwin
Platform: win32
Classifier: Programming Language :: Python :: 3.9
Classifier: Programming Language :: Python :: 3.8
Requires-Python: >=3.6
License-File: LICENSE
Requires-Dist: biopython (>=1)
Requires-Dist: pandas (>=1)
Requires-Dist: tqdm (>=4)
Requires-Dist: seaborn (>=0)
Requires-Dist: pygad (>=2)
Requires-Dist: numpy (>=1)
Requires-Dist: matplotlib (>=3)
Requires-Dist: colored (>=1)
Provides-Extra: testing
Requires-Dist: pytest (>=6.0) ; extra == 'testing'
Requires-Dist: pytest-cov (>=2.0) ; extra == 'testing'
Requires-Dist: mypy (>=0.910) ; extra == 'testing'
Requires-Dist: flake8 (>=3.9) ; extra == 'testing'
Requires-Dist: tox (>=3.24) ; extra == 'testing'
